impynb/__init__.py
impynb/import_context.py
impynb/notebook_finder.py
impynb/notebook_loader.py
impynb/util/__init__.py
impynb/util/get_notebook_path.py
impynb/util/is_runnable_cell.py
impynb/util/is_running_in_notebook.py
impynb-0.1.7.dist-info/METADATA
impynb-0.1.7.dist-info/WHEEL
impynb-0.1.7.dist-info/licenses/LICENSE
impynb-0.1.7.dist-info/RECORD
