Metadata-Version: 2.4
Name: impynb
Version: 0.1.7
Summary: Import Jupyter notebooks as Python modules
License-File: LICENSE
Author: Steffen Hirte
Author-email: shirte@users.noreply.github.com
Requires-Python: >=3.9,<4
Classifier: Programming Language :: Python :: 3
Classifier: Programming Language :: Python :: 3.9
Classifier: Programming Language :: Python :: 3.10
Classifier: Programming Language :: Python :: 3.11
Classifier: Programming Language :: Python :: 3.12
Classifier: Programming Language :: Python :: 3.13
Classifier: Programming Language :: Python :: 3.14
Requires-Dist: ipykernel (>=6,<8)
Requires-Dist: nbformat (>=5,<6)
